[
    {
        "page_content": "Son Dakika Haberler\n\nSICAK\n\nGÜNDEM\n\nTÜRKİYE\n\nDÜNYA\n\nTÜRK DÜNYASI\n\nEKONOMİ\n\nSPOR\n\nSAVUNMA\n\nÇOCUK\n\nÖZEL HABER\n\nDOSYA HABER\n\nDİĞER\n\nSON HABERLER\n\nTÜM MANŞETLER\n\nFOTO FOKUS\n\nDÜNYA DIŞI\n\nVİDEO GALERİ\n\nKÜLTÜR-SANAT\n\nDOSYA HABER\n\nYAŞAM\n\nSAĞLIK\n\nGEZİ\n\nTEKNOLOJİ\n\nÇEVRE\n\nEĞİTİM\n\nGÜNCEL\n\nÇOCUK\n\nPODCAST\n\nHAVA DURUMU\n\nTRT'DEN HABERLER\n\nHAVA UYARILARI\n\nTRT AKADEMİ\n\nPROGRAMLAR\n\nTRT ARŞİV\n\nParçalı Bulutlu\n\n8.2ºC Ankara\n\n\n\nAdana\n\nAdıyaman\n\nAfyonkarahisar\n\nAğrı\n\nAksaray\n\nAmasya\n\nAnkara\n\nAntalya\n\nArdahan\n\nArtvin\n\nAydın\n\nBalıkesir\n\nBartın\n\nBatman\n\nBayburt\n\nBilecik\n\nBingöl\n\nBitlis\n\nBolu\n\nBurdur\n\nBursa\n\nÇanakkale\n\nÇankırı\n\nÇorum\n\nDenizli\n\nDiyarbakır\n\nDüzce\n\nEdirne\n\nElazığ\n\nErzincan\n\nErzurum\n\nEskişehir\n\nGaziantep\n\nGiresun\n\nGümüşhane\n\nHakkari\n\nHatay\n\nIğdır\n\nIsparta\n\nİstanbul\n\nİzmir\n\nKahramanmaraş\n\nKarabük\n\nKaraman\n\nKars\n\nKastamonu\n\nKayseri\n\nKırıkkale\n\nKırklareli\n\nKırşehir\n\nKilis\n\nKocaeli\n\nKonya\n\nKütahya\n\nMalatya\n\nManisa\n\nMardin\n\nMersin\n\nMuğla\n\nMuş\n\nNevşehir\n\nNiğde\n\nOrdu\n\nOsmaniye\n\nRize\n\nSakarya\n\nSamsun\n\nSiirt\n\nSinop\n\nSivas\n\nŞanlıurfa\n\nŞırnak\n\nTekirdağ\n\nTokat\n\nTrabzon\n\nTunceli\n\nUşak\n\nVan\n\nYalova\n\nYozgat\n\nZonguldak\n\n\n\nCanlı TV\n\nCANLI\n\nArama\n\n\n\nArama\n\nAnasayfa\n\nGündem\n\nTürkiye\n\nDünya\n\nTürk Dünyası\n\nEkonomi\n\nSpor\n\nSavunma\n\nÇocuk\n\nÖzel Haber\n\nİnfografik\n\nİnteraktif\n\nHava Durumu\n\nHava Uyarıları\n\nDiğer\n\n- Son Haberler\n\n- Tüm Manşetler\n\n- Foto Fokus\n\n- Video Galeri\n\n- Dosya Haber\n\n- Sağlık\n\n- Yaşam\n\n- Gezi\n\n- Teknoloji\n\n- Eğitim\n\n- Dünya Dışı\n\n- Kültür-Sanat\n\n- Çevre\n\n- Güncel\n\n- Podcast\n\n- Programlar\n\n- TRT'den Haberler\n\n- TRT Akademi\n\n- TRT Arşiv\n\n- Yayın Akışı\n\n- Radyo Frekanslarımız\n\n- Sitene Ekle\n\n- İletişim\n\n- Gizlilik Politikası ve Aydınlatma Metni\n\n- Kullanım Şartları\n\n- Çerez Politikası\n\nABD-İran gerilimi Haberleri\n\nCENTCOM: Saldırılarda 3 ABD askeri öldü\n\nABD Merkez Kuvvetler Komutanlığı (CENTCOM), İran'a yönelik operasyonlarda 3 ABD askerinin öldüğünü, 5'inin ağır yaralandığını duyurdu.\n\nABD: Umman Körfezi'nde bir İran gemisini vurduk\n\nİran'dan İsrail ve ABD'ye: Onları daha önce hiç karşılaşmadıkları bir güçle vuracağız\n\nPezeşkiyan: Hamaney'in intikamını almayı görev ve meşru bir hak olarak görüyoruz\n\nTrump'tan İran mesajı: Ağır darbe alıyorlar\n\nPortre: Ayetullah Ali Hamaney kimdir?\n\nFoto Fokus\n\nTÜMÜNÜ GÖR\n\n#ABD-İran gerilimi\n\nNew York'ta İran'a saldırılar protesto edildi\n\nBeyaz Saray önünde İran'a saldırılar protesto edildi\n\nİran'ın misillemesinde bir füze Tel Aviv'e isabet etti\n\nDiğer Haberler\n\nPakistan'da bir grup gösterici, ABD'nin Karaçi Konsolosluğu'na girmeye çalıştı\n\n01.03.2026 10:55\n\nİran, ABD ve İsrail'e ait noktalara saldırı başlattı\n\n01.03.2026 07:58\n\nİran'da Hamaney'in ölümünün ardından gösteriler düzenlendi\n\n01.03.2026 07:21\n\nİran Devrim Muhafızları: İsrail ve ABD üslerine saldırılar başlayacak\n\n01.03.2026 05:34\n\nABD Savunma Bakanı Hegseth: İran asla nükleer silaha sahip olamayacak\n\n01.03.2026 05:29\n\nHamaney'in kızı, damadı, torunu ve gelini hayatını kaybetti\n\n01.03.2026 03:30\n\nİran'ın BM Temsilcisi: ABD ve İsrail, sadece İran'a değil uluslararası hukuka da savaş açtı\n\n01.03.2026 03:28\n\nTrump'ın İran'a saldırı kararı Cumhuriyetçi tabandan tepki gördü\n\n01.03.2026 02:03\n\nBM: İran'a müdahale bölgede kontrol edilemeyecek olayları tetikleme riski taşıyor\n\n01.03.2026 01:56\n\nKatar ve Kuveyt, İran'dan düzenlenen saldırılara karşı koyduklarını duyurdu\n\n01.03.2026 01:08\n\nDMM’den, \"Türkiye'nin İran'a yönelik saldırılara destek verdiği\" iddialarına yalanlama\n\n28.02.2026 16:42\n\nUmman Dışişleri Bakanı, İran'ın uranyum stokunun sıfırlanacağını söyledi\n\n28.02.2026 04:16\n\nABD Başkan Yardımcısı Vance: İran'ın nükleer silah üretmeye çalıştığına ilişkin kanıt gördük\n\n26.02.2026 11:54\n\nİranlı diplomatik heyet ABD ile müzakerelere katılmak üzere Cenevre'ye gitti\n\n25.02.2026 17:49\n\nYükleniyor lütfen bekleyiniz",
        "metadata": {
            "source": "https://www.trthaber.com/etiket/abd-iran-gerilimi/",
            "title": "Haberleri | TRT Haber",
            "description": " Haberleri",
            "language": "tr",
            "scraped_at": "2026-03-01 18:18:38",
            "source_url": "https://www.trthaber.com/etiket/abd-iran-gerilimi/"
        }
    }
]